pprl_client/__init__.py
pprl_client/_cli.py
pprl_client/_client.py
pprl_client/_estimate.py
pprl_client/_model.py
pprl_client/main.py
pprl_client/types.py
pprl_client-0.4.0.dist-info/LICENSE
pprl_client-0.4.0.dist-info/METADATA
pprl_client-0.4.0.dist-info/WHEEL
pprl_client-0.4.0.dist-info/entry_points.txt
pprl_client-0.4.0.dist-info/RECORD
