Metadata-Version: 2.3
Name: pprl-client
Version: 0.4.0
Summary: HTTP-based client for interacting with a service for privacy-preserving record linkage with Bloom filters.
License: MIT
Keywords: record linkage,privacy,bloom filter,bitarray,cryptography,service,client,cli
Author: Maximilian Jugl
Author-email: Maximilian.Jugl@medizin.uni-leipzig.de
Requires-Python: >=3.10,<4
Classifier: Development Status :: 4 - Beta
Classifier: Environment :: Console
Classifier: Intended Audience :: Developers
Classifier: Intended Audience :: Education
Classifier: Intended Audience :: End Users/Desktop
Classifier: Intended Audience :: Information Technology
Classifier: Intended Audience :: Science/Research
Classifier: Topic :: Scientific/Engineering
Classifier: Topic :: Security :: Cryptography
Classifier: Topic :: Software Development :: Libraries :: Python Modules
Provides-Extra: faker
Requires-Dist: click (>=8.0.0,<9.0.0)
Requires-Dist: faker (>=26.0.0) ; extra == "faker"
Requires-Dist: httpx (>=0.28.0,<0.29.0)
Requires-Dist: pprl-core (>=0.1.4,<0.2.0)
Requires-Dist: pprl-model (>=0.1.6,<0.2.0)
Project-URL: Repository, https://github.com/ul-mds/pprl-client
